{"data":{"repository":{"pullRequest":{"reviewThreads":{"pageInfo":{"hasNextPage":true,"endCursor":"Y3Vyc29yOnYyOpK0MjAyNS0xMS0xMlQxOTo1NTozNFrOYbl0qg=="},"nodes":[{"id":"PRRT_kwDOKSXUF85hLZvj","isResolved":true},{"id":"PRRT_kwDOKSXUF85hLZvm","isResolved":true},{"id":"PRRT_kwDOKSXUF85hLZvn","isResolved":true},{"id":"PRRT_kwDOKSXUF85hLZvo","isResolved":true},{"id":"PRRT_kwDOKSXUF85hLZvr","isResolved":true},{"id":"PRRT_kwDOKSXUF85hOiwA","isResolved":true},{"id":"PRRT_kwDOKSXUF85hOiwD","isResolved":true},{"id":"PRRT_kwDOKSXUF85hOiwF","isResolved":true},{"id":"PRRT_kwDOKSXUF85hOiwH","isResolved":true},{"id":"PRRT_kwDOKSXUF85hbeVE","isResolved":true},{"id":"PRRT_kwDOKSXUF85hbeVK","isResolved":true},{"id":"PRRT_kwDOKSXUF85hbeVV","isResolved":true},{"id":"PRRT_kwDOKSXUF85hbeVb","isResolved":true},{"id":"PRRT_kwDOKSXUF85hbeVf","isResolved":true},{"id":"PRRT_kwDOKSXUF85hboue","isResolved":true},{"id":"PRRT_kwDOKSXUF85hbouj","isResolved":true},{"id":"PRRT_kwDOKSXUF85hboum","isResolved":true},{"id":"PRRT_kwDOKSXUF85hbouo","isResolved":true},{"id":"PRRT_kwDOKSXUF85hbout","isResolved":true},{"id":"PRRT_kwDOKSXUF85hcGMS","isResolved":true},{"id":"PRRT_kwDOKSXUF85hcGMX","isResolved":true},{"id":"PRRT_kwDOKSXUF85hcGMl","isResolved":true},{"id":"PRRT_kwDOKSXUF85hcGMt","isResolved":true},{"id":"PRRT_kwDOKSXUF85hcGMz","isResolved":true},{"id":"PRRT_kwDOKSXUF85hcGNA","isResolved":true},{"id":"PRRT_kwDOKSXUF85hcGNK","isResolved":true},{"id":"PRRT_kwDOKSXUF85hcGNR","isResolved":true},{"id":"PRRT_kwDOKSXUF85hcGNX","isResolved":true},{"id":"PRRT_kwDOKSXUF85hcGNf","isResolved":true},{"id":"PRRT_kwDOKSXUF85hcGNm","isResolved":true},{"id":"PRRT_kwDOKSXUF85hcGNs","isResolved":true},{"id":"PRRT_kwDOKSXUF85hcGN5","isResolved":true},{"id":"PRRT_kwDOKSXUF85hcGOB","isResolved":true},{"id":"PRRT_kwDOKSXUF85hcGOG","isResolved":true},{"id":"PRRT_kwDOKSXUF85hcSed","isResolved":true},{"id":"PRRT_kwDOKSXUF85hcSep","isResolved":true},{"id":"PRRT_kwDOKSXUF85hcSe4","isResolved":true},{"id":"PRRT_kwDOKSXUF85hcSfA","isResolved":true},{"id":"PRRT_kwDOKSXUF85hcSfE","isResolved":true},{"id":"PRRT_kwDOKSXUF85hcSfJ","isResolved":true},{"id":"PRRT_kwDOKSXUF85hcSfP","isResolved":true},{"id":"PRRT_kwDOKSXUF85hcSfV","isResolved":true},{"id":"PRRT_kwDOKSXUF85hcSfb","isResolved":true},{"id":"PRRT_kwDOKSXUF85hcSfj","isResolved":true},{"id":"PRRT_kwDOKSXUF85hcSfs","isResolved":true},{"id":"PRRT_kwDOKSXUF85hcSf5","isResolved":true},{"id":"PRRT_kwDOKSXUF85hcSgE","isResolved":true},{"id":"PRRT_kwDOKSXUF85hcSgJ","isResolved":true},{"id":"PRRT_kwDOKSXUF85hcSgM","isResolved":true},{"id":"PRRT_kwDOKSXUF85hcSgQ","isResolved":true},{"id":"PRRT_kwDOKSXUF85hg5_t","isResolved":true},{"id":"PRRT_kwDOKSXUF85hg5_5","isResolved":true},{"id":"PRRT_kwDOKSXUF85hg6AI","isResolved":true},{"id":"PRRT_kwDOKSXUF85hg6AV","isResolved":true},{"id":"PRRT_kwDOKSXUF85hg6Ah","isResolved":true},{"id":"PRRT_kwDOKSXUF85hg6As","isResolved":true},{"id":"PRRT_kwDOKSXUF85hg6A_","isResolved":true},{"id":"PRRT_kwDOKSXUF85hg6BL","isResolved":true},{"id":"PRRT_kwDOKSXUF85hie7x","isResolved":true},{"id":"PRRT_kwDOKSXUF85hie73","isResolved":true},{"id":"PRRT_kwDOKSXUF85hie77","isResolved":true},{"id":"PRRT_kwDOKSXUF85hjEh5","isResolved":true},{"id":"PRRT_kwDOKSXUF85hjEiF","isResolved":true},{"id":"PRRT_kwDOKSXUF85hjEiP","isResolved":true},{"id":"PRRT_kwDOKSXUF85hjEiT","isResolved":true},{"id":"PRRT_kwDOKSXUF85hjEig","isResolved":true},{"id":"PRRT_kwDOKSXUF85hjEip","isResolved":true},{"id":"PRRT_kwDOKSXUF85hjEi1","isResolved":true},{"id":"PRRT_kwDOKSXUF85hjEjD","isResolved":true},{"id":"PRRT_kwDOKSXUF85hjEjV","isResolved":true},{"id":"PRRT_kwDOKSXUF85hjEjg","isResolved":true},{"id":"PRRT_kwDOKSXUF85hkQdm","isResolved":true},{"id":"PRRT_kwDOKSXUF85hkQdr","isResolved":true},{"id":"PRRT_kwDOKSXUF85hkQdw","isResolved":true},{"id":"PRRT_kwDOKSXUF85hkUWb","isResolved":true},{"id":"PRRT_kwDOKSXUF85hkUWf","isResolved":true},{"id":"PRRT_kwDOKSXUF85hkUWk","isResolved":true},{"id":"PRRT_kwDOKSXUF85hkUWq","isResolved":true},{"id":"PRRT_kwDOKSXUF85hkjRT","isResolved":true},{"id":"PRRT_kwDOKSXUF85hkjRg","isResolved":true},{"id":"PRRT_kwDOKSXUF85hkjRj","isResolved":true},{"id":"PRRT_kwDOKSXUF85hlkT2","isResolved":true},{"id":"PRRT_kwDOKSXUF85hlkT7","isResolved":true},{"id":"PRRT_kwDOKSXUF85hlur-","isResolved":true},{"id":"PRRT_kwDOKSXUF85hlusG","isResolved":true},{"id":"PRRT_kwDOKSXUF85hmHld","isResolved":true},{"id":"PRRT_kwDOKSXUF85hmHll","isResolved":true},{"id":"PRRT_kwDOKSXUF85hmHln","isResolved":true},{"id":"PRRT_kwDOKSXUF85hmHlp","isResolved":true},{"id":"PRRT_kwDOKSXUF85hmHlx","isResolved":true},{"id":"PRRT_kwDOKSXUF85hmHlz","isResolved":true},{"id":"PRRT_kwDOKSXUF85hmHl3","isResolved":true},{"id":"PRRT_kwDOKSXUF85hrQtL","isResolved":true},{"id":"PRRT_kwDOKSXUF85hrQta","isResolved":true},{"id":"PRRT_kwDOKSXUF85huXSB","isResolved":true},{"id":"PRRT_kwDOKSXUF85huXSM","isResolved":true},{"id":"PRRT_kwDOKSXUF85huXSO","isResolved":true},{"id":"PRRT_kwDOKSXUF85huXSV","isResolved":true},{"id":"PRRT_kwDOKSXUF85huXSc","isResolved":true},{"id":"PRRT_kwDOKSXUF85huXSq","isResolved":true}]}}}}}